rapid_tasty_api/__init__.py
rapid_tasty_api/_client.py
rapid_tasty_api/_constants.py
rapid_tasty_api/data.py
rapid_tasty_api/feed.py
rapid_tasty_api/py.typed
rapid_tasty_api/tag.py
rapid_tasty_api/tip.py
rapid_tasty_api/recipe/__init__.py
rapid_tasty_api/recipe/completion.py
rapid_tasty_api/recipe/component.py
rapid_tasty_api/recipe/credit.py
rapid_tasty_api/recipe/ingredient.py
rapid_tasty_api/recipe/instruction.py
rapid_tasty_api/recipe/measurement.py
rapid_tasty_api/recipe/nutrition.py
rapid_tasty_api/recipe/price.py
rapid_tasty_api/recipe/py.typed
rapid_tasty_api/recipe/ratings.py
rapid_tasty_api/recipe/recipe.py
rapid_tasty_api/recipe/section.py
rapid_tasty_api/recipe/topic.py
rapid_tasty_api-0.1.3.dist-info/METADATA
rapid_tasty_api-0.1.3.dist-info/WHEEL
rapid_tasty_api-0.1.3.dist-info/licenses/LICENSE
rapid_tasty_api-0.1.3.dist-info/RECORD
