Metadata-Version: 2.3
Name: rapid_tasty_api
Version: 0.1.3
Summary: Typed Python wrapper for the Tasty API on RapidAPI.
Project-URL: Repository, https://github.com/KianKhadempour/TastyAPI.git
Project-URL: Issues, https://github.com/KianKhadempour/TastyAPI/issues
Author: Kian Khadempour
License: MIT License
License-File: LICENSE
Classifier: Development Status :: 3 - Alpha
Classifier: Intended Audience :: Developers
Classifier: License :: OSI Approved :: MIT License
Classifier: Programming Language :: Python :: 3
Classifier: Programming Language :: Python :: 3.11
Classifier: Programming Language :: Python :: 3.12
Classifier: Programming Language :: Python :: Implementation :: CPython
Classifier: Typing :: Typed
Requires-Python: >=3.11
Requires-Dist: pycountry>=23.12.11
Requires-Dist: python-iso639>=2024.4.27
Requires-Dist: requests>=2.32.2
